README.md
setup.py
dash_utils/dash_utils.py
dash_utils/keycloak_utils.py
ems_dash_utils.egg-info/PKG-INFO
ems_dash_utils.egg-info/SOURCES.txt
ems_dash_utils.egg-info/dependency_links.txt
ems_dash_utils.egg-info/requires.txt
ems_dash_utils.egg-info/top_level.txt