Metadata-Version: 2.1
Name: ems-dash-utils
Version: 0.0.1
Summary: A utility package for dash apps
Home-page: https://github.com/
Author: Jesper Halkjær Jensen
Author-email: gedemagt@gmail.com
License: MIT
Platform: UNKNOWN
Requires-Python: >=3.6
